nunchaku/_C.cpython-310-x86_64-linux-gnu.so
nunchaku/__init__.py
nunchaku/__version__.py
nunchaku/test.py
nunchaku/utils.py
nunchaku/caching/__init__.py
nunchaku/caching/utils.py
nunchaku/caching/diffusers_adapters/__init__.py
nunchaku/caching/diffusers_adapters/flux.py
nunchaku/caching/diffusers_adapters/sana.py
nunchaku/csrc/flux.h
nunchaku/csrc/gemm.h
nunchaku/csrc/gemm88.h
nunchaku/csrc/module.h
nunchaku/csrc/ops.h
nunchaku/csrc/pybind.cpp
nunchaku/csrc/sana.h
nunchaku/csrc/utils.h
nunchaku/lora/__init__.py
nunchaku/lora/flux/__init__.py
nunchaku/lora/flux/compose.py
nunchaku/lora/flux/convert.py
nunchaku/lora/flux/diffusers_converter.py
nunchaku/lora/flux/nunchaku_converter.py
nunchaku/lora/flux/packer.py
nunchaku/lora/flux/utils.py
nunchaku/models/__init__.py
nunchaku/models/safety_checker.py
nunchaku/models/text_encoders/__init__.py
nunchaku/models/text_encoders/linear.py
nunchaku/models/text_encoders/t5_encoder.py
nunchaku/models/text_encoders/tinychat_utils.py
nunchaku/models/transformers/__init__.py
nunchaku/models/transformers/transformer_flux.py
nunchaku/models/transformers/transformer_sana.py
nunchaku/models/transformers/utils.py
nunchaku_kaggle-0.2.0.dist-info/LICENCE.txt
nunchaku_kaggle-0.2.0.dist-info/METADATA
nunchaku_kaggle-0.2.0.dist-info/WHEEL
nunchaku_kaggle-0.2.0.dist-info/top_level.txt
nunchaku_kaggle-0.2.0.dist-info/RECORD
